{
  "classname": null,
  "name": null,
  "animation": {
    "classname": null,
    "name": "AnimationManager",
    "actionlist": []
  },
  "dataScale": 1,
  "designHeight": 640,
  "designWidth": 1136,
  "textures": [
    "settingWidgetPlist.plist"
  ],
  "texturesPng": [
    "settingWidgetPlist.plist"
  ],
  "version": "1.6.0.0",
  "widgetTree": {
    "classname": "Panel",
    "name": null,
    "children": [
      {
        "classname": "ImageView",
        "name": null,
        "children": [
          {
            "classname": "ImageView",
            "name": null,
            "children": [],
            "options": {
              "__type": "ImageViewSurrogate:#EditorCommon.JsonModel.Component.GUI",
              "classname": "ImageView",
              "name": "ImageTilteBg",
              "ZOrder": 0,
              "actiontag": 48237819,
              "anchorPointX": 0.5,
              "anchorPointY": 0.5,
              "classType": "CocoStudio.EngineAdapterWrap.CSImageView",
              "colorB": 255,
              "colorG": 255,
              "colorR": 255,
              "customProperty": "",
              "flipX": false,
              "flipY": false,
              "height": 68,
              "ignoreSize": false,
              "layoutParameter": null,
              "opacity": 255,
              "positionPercentX": 0,
              "positionPercentY": 0.413333327,
              "positionType": 0,
              "rotation": 0,
              "scaleX": 1,
              "scaleY": 1,
              "sizePercentX": 0.995098054,
              "sizePercentY": 0.151111111,
              "sizeType": 0,
              "tag": 43,
              "touchAble": false,
              "useMergedTexture": false,
              "visible": true,
              "width": 406,
              "x": 0,
              "y": 186,
              "capInsetsHeight": 10,
              "capInsetsWidth": 13,
              "capInsetsX": 20,
              "capInsetsY": 25,
              "fileName": null,
              "fileNameData": {
                "path": "u_bg_game_chat.png",
                "plistFile": "talkWidgetPlist.plist",
                "resourceType": 1
              },
              "scale9Enable": true,
              "scale9Height": 68,
              "scale9Width": 406
            }
          },
          {
            "classname": "ImageView",
            "name": null,
            "children": [
              {
                "classname": "ListView",
                "name": null,
                "children": [],
                "options": {
                  "__type": "ListViewSurrogate:#EditorCommon.JsonModel.Component.GUI",
                  "classname": "ListView",
                  "name": "ListView_19",
                  "ZOrder": 0,
                  "actiontag": 32468373,
                  "anchorPointX": 0,
                  "anchorPointY": 0,
                  "classType": "CocoStudio.EngineAdapterWrap.CSListView",
                  "colorB": 255,
                  "colorG": 255,
                  "colorR": 255,
                  "customProperty": "",
                  "flipX": false,
                  "flipY": false,
                  "height": 280,
                  "ignoreSize": false,
                  "layoutParameter": null,
                  "opacity": 255,
                  "positionPercentX": -0.475195825,
                  "positionPercentY": -0.443038,
                  "positionType": 0,
                  "rotation": 0,
                  "scaleX": 1,
                  "scaleY": 1,
                  "sizePercentX": 0.95039165,
                  "sizePercentY": 0.886076,
                  "sizeType": 0,
                  "tag": 46,
                  "touchAble": true,
                  "useMergedTexture": false,
                  "visible": true,
                  "width": 364,
                  "x": -182,
                  "y": -140,
                  "backGroundImage": null,
                  "backGroundImageData": null,
                  "backGroundScale9Enable": false,
                  "bgColorB": 255,
                  "bgColorG": 150,
                  "bgColorOpacity": 100,
                  "bgColorR": 150,
                  "bgEndColorB": 255,
                  "bgEndColorG": 150,
                  "bgEndColorR": 150,
                  "bgStartColorB": 255,
                  "bgStartColorG": 255,
                  "bgStartColorR": 255,
                  "bounceEnable": false,
                  "capInsetsHeight": 1,
                  "capInsetsWidth": 1,
                  "capInsetsX": 0,
                  "capInsetsY": 0,
                  "clipAble": true,
                  "colorType": 0,
                  "direction": 1,
                  "editorClipAble": false,
                  "gravity": 2,
                  "innerHeight": 0,
                  "innerWidth": 0,
                  "itemMargin": 0,
                  "vectorX": 0,
                  "vectorY": -0.5
                }
              }
            ],
            "options": {
              "__type": "ImageViewSurrogate:#EditorCommon.JsonModel.Component.GUI",
              "classname": "ImageView",
              "name": "ImageCBg",
              "ZOrder": 0,
              "actiontag": 37217564,
              "anchorPointX": 0.5,
              "anchorPointY": 0.5,
              "classType": "CocoStudio.EngineAdapterWrap.CSImageView",
              "colorB": 255,
              "colorG": 255,
              "colorR": 255,
              "customProperty": "",
              "flipX": false,
              "flipY": false,
              "height": 316,
              "ignoreSize": false,
              "layoutParameter": null,
              "opacity": 255,
              "positionPercentX": 0,
              "positionPercentY": -0.0155555559,
              "positionType": 0,
              "rotation": 0,
              "scaleX": 1,
              "scaleY": 1,
              "sizePercentX": 0.9387255,
              "sizePercentY": 0.7022222,
              "sizeType": 0,
              "tag": 45,
              "touchAble": false,
              "useMergedTexture": false,
              "visible": true,
              "width": 383,
              "x": 0,
              "y": -7,
              "capInsetsHeight": 2,
              "capInsetsWidth": 2,
              "capInsetsX": 35,
              "capInsetsY": 35,
              "fileName": null,
              "fileNameData": {
                "path": "u_bounced_bg2.png",
                "plistFile": "talkWidgetPlist.plist",
                "resourceType": 1
              },
              "scale9Enable": true,
              "scale9Height": 316,
              "scale9Width": 383
            }
          },
          {
            "classname": "ImageView",
            "name": null,
            "children": [
              {
                "classname": "TextField",
                "name": null,
                "children": [],
                "options": {
                  "__type": "TextFieldSurrogate:#EditorCommon.JsonModel.Component.GUI",
                  "classname": "TextField",
                  "name": "TextField_23",
                  "ZOrder": 0,
                  "actiontag": 7535426,
                  "anchorPointX": 0.5,
                  "anchorPointY": 0.5,
                  "classType": "CocoStudio.EngineAdapterWrap.CSTextField",
                  "colorB": 0,
                  "colorG": 0,
                  "colorR": 0,
                  "customProperty": "",
                  "flipX": false,
                  "flipY": false,
                  "height": 35,
                  "ignoreSize": false,
                  "layoutParameter": null,
                  "opacity": 127,
                  "positionPercentX": 0,
                  "positionPercentY": 0,
                  "positionType": 0,
                  "rotation": 0,
                  "scaleX": 1,
                  "scaleY": 1,
                  "sizePercentX": 0.969697,
                  "sizePercentY": 0.795454562,
                  "sizeType": 0,
                  "tag": 50,
                  "touchAble": true,
                  "useMergedTexture": false,
                  "visible": true,
                  "width": 320,
                  "x": 0,
                  "y": 0,
                  "areaHeight": 35,
                  "areaWidth": 320,
                  "fontFile": null,
                  "fontName": "微软雅黑",
                  "fontSize": 25,
                  "maxLength": 20,
                  "maxLengthEnable": true,
                  "passwordEnable": false,
                  "passwordStyleText": "*",
                  "placeHolder": "说点什么吧",
                  "text": ""
                }
              }
            ],
            "options": {
              "__type": "ImageViewSurrogate:#EditorCommon.JsonModel.Component.GUI",
              "classname": "ImageView",
              "name": "ImageEditBg",
              "ZOrder": 0,
              "actiontag": 61694733,
              "anchorPointX": 0.5,
              "anchorPointY": 0.5,
              "classType": "CocoStudio.EngineAdapterWrap.CSImageView",
              "colorB": 255,
              "colorG": 255,
              "colorR": 255,
              "customProperty": "",
              "flipX": false,
              "flipY": false,
              "height": 44,
              "ignoreSize": false,
              "layoutParameter": null,
              "opacity": 255,
              "positionPercentX": -0.06127451,
              "positionPercentY": -0.4288889,
              "positionType": 0,
              "rotation": 0,
              "scaleX": 1,
              "scaleY": 1,
              "sizePercentX": 0.8088235,
              "sizePercentY": 0.09777778,
              "sizeType": 0,
              "tag": 49,
              "touchAble": false,
              "useMergedTexture": false,
              "visible": true,
              "width": 330,
              "x": -25,
              "y": -193,
              "capInsetsHeight": 2,
              "capInsetsWidth": 2,
              "capInsetsX": 20,
              "capInsetsY": 10,
              "fileName": null,
              "fileNameData": {
                "path": "image_input_bg.png",
                "plistFile": "talkWidgetPlist.plist",
                "resourceType": 1
              },
              "scale9Enable": true,
              "scale9Height": 44,
              "scale9Width": 330
            }
          },
          {
            "classname": "Button",
            "name": null,
            "children": [
              {
                "classname": "ImageView",
                "name": null,
                "children": [],
                "options": {
                  "__type": "ImageViewSurrogate:#EditorCommon.JsonModel.Component.GUI",
                  "classname": "ImageView",
                  "name": "FontSend",
                  "ZOrder": 0,
                  "actiontag": 12714810,
                  "anchorPointX": 0.5,
                  "anchorPointY": 0.5,
                  "classType": "CocoStudio.EngineAdapterWrap.CSImageView",
                  "colorB": 255,
                  "colorG": 255,
                  "colorR": 255,
                  "customProperty": "",
                  "flipX": false,
                  "flipY": false,
                  "height": 28,
                  "ignoreSize": true,
                  "layoutParameter": null,
                  "opacity": 255,
                  "positionPercentX": 0,
                  "positionPercentY": 0,
                  "positionType": 0,
                  "rotation": 0,
                  "scaleX": 1,
                  "scaleY": 1,
                  "sizePercentX": 0.5339806,
                  "sizePercentY": 0.4375,
                  "sizeType": 0,
                  "tag": 52,
                  "touchAble": false,
                  "useMergedTexture": false,
                  "visible": true,
                  "width": 55,
                  "x": 0,
                  "y": 0,
                  "capInsetsHeight": 1,
                  "capInsetsWidth": 1,
                  "capInsetsX": 0,
                  "capInsetsY": 0,
                  "fileName": null,
                  "fileNameData": {
                    "path": "u_game_text_send.png",
                    "plistFile": "talkWidgetPlist.plist",
                    "resourceType": 1
                  },
                  "scale9Enable": false,
                  "scale9Height": 28,
                  "scale9Width": 55
                }
              }
            ],
            "options": {
              "__type": "ButtonSurrogate:#EditorCommon.JsonModel.Component.GUI",
              "classname": "Button",
              "name": "ButtonSend",
              "ZOrder": 0,
              "actiontag": 46188169,
              "anchorPointX": 0.5,
              "anchorPointY": 0.5,
              "classType": "CocoStudio.EngineAdapterWrap.CSButton",
              "colorB": 255,
              "colorG": 255,
              "colorR": 255,
              "customProperty": "",
              "flipX": false,
              "flipY": false,
              "height": 64,
              "ignoreSize": true,
              "layoutParameter": null,
              "opacity": 255,
              "positionPercentX": 0.365196079,
              "positionPercentY": -0.4288889,
              "positionType": 0,
              "rotation": 0,
              "scaleX": 0.799999952,
              "scaleY": 0.799999952,
              "sizePercentX": 0.252450973,
              "sizePercentY": 0.142222226,
              "sizeType": 0,
              "tag": 51,
              "touchAble": true,
              "useMergedTexture": false,
              "visible": true,
              "width": 103,
              "x": 149,
              "y": -193,
              "capInsetsHeight": 1,
              "capInsetsWidth": 1,
              "capInsetsX": 0,
              "capInsetsY": 0,
              "disabled": null,
              "disabledData": {
                "path": null,
                "plistFile": null,
                "resourceType": 0
              },
              "fontName": "微软雅黑",
              "fontSize": 14,
              "fontType": 0,
              "normal": null,
              "normalData": {
                "path": "image_send_bg.png",
                "plistFile": "talkWidgetPlist.plist",
                "resourceType": 1
              },
              "pressed": null,
              "pressedData": {
                "path": "image_send_bg.png",
                "plistFile": "talkWidgetPlist.plist",
                "resourceType": 1
              },
              "scale9Enable": false,
              "scale9Height": 64,
              "scale9Width": 103,
              "text": "",
              "textColorB": 255,
              "textColorG": 255,
              "textColorR": 255
            }
          },
          {
            "classname": "ImageView",
            "name": null,
            "children": [
              {
                "classname": "CheckBox",
                "name": null,
                "children": [],
                "options": {
                  "__type": "CheckBoxSurrogate:#EditorCommon.JsonModel.Component.GUI",
                  "classname": "CheckBox",
                  "name": "CheckBoxFace",
                  "ZOrder": 0,
                  "actiontag": 18552114,
                  "anchorPointX": 0.5,
                  "anchorPointY": 0.5,
                  "classType": "CocoStudio.EngineAdapterWrap.CSCheckBox",
                  "colorB": 255,
                  "colorG": 255,
                  "colorR": 255,
                  "customProperty": "",
                  "flipX": false,
                  "flipY": false,
                  "height": 45,
                  "ignoreSize": true,
                  "layoutParameter": null,
                  "opacity": 255,
                  "positionPercentX": -0.244791672,
                  "positionPercentY": -0.0238095243,
                  "positionType": 0,
                  "rotation": 0,
                  "scaleX": 1,
                  "scaleY": 1,
                  "sizePercentX": 0.5,
                  "sizePercentY": 1.07142854,
                  "sizeType": 0,
                  "tag": 57,
                  "touchAble": true,
                  "useMergedTexture": false,
                  "visible": true,
                  "width": 192,
                  "x": -94,
                  "y": -1,
                  "backGroundBox": null,
                  "backGroundBoxData": {
                    "path": "image_checkbox_face.png",
                    "plistFile": "talkWidgetPlist.plist",
                    "resourceType": 1
                  },
                  "backGroundBoxDisabled": null,
                  "backGroundBoxDisabledData": {
                    "path": null,
                    "plistFile": null,
                    "resourceType": 0
                  },
                  "backGroundBoxSelected": null,
                  "backGroundBoxSelectedData": {
                    "path": "image_checkbox_face.png",
                    "plistFile": "talkWidgetPlist.plist",
                    "resourceType": 1
                  },
                  "frontCross": null,
                  "frontCrossData": {
                    "path": "u_game_btn_chat_press1.png",
                    "plistFile": "talkWidgetPlist.plist",
                    "resourceType": 1
                  },
                  "frontCrossDisabled": null,
                  "frontCrossDisabledData": {
                    "path": null,
                    "plistFile": null,
                    "resourceType": 0
                  },
                  "selectedState": true
                }
              },
              {
                "classname": "CheckBox",
                "name": null,
                "children": [],
                "options": {
                  "__type": "CheckBoxSurrogate:#EditorCommon.JsonModel.Component.GUI",
                  "classname": "CheckBox",
                  "name": "CheckBoxLan",
                  "ZOrder": 0,
                  "actiontag": 12938832,
                  "anchorPointX": 0.5,
                  "anchorPointY": 0.5,
                  "classType": "CocoStudio.EngineAdapterWrap.CSCheckBox",
                  "colorB": 255,
                  "colorG": 255,
                  "colorR": 255,
                  "customProperty": "",
                  "flipX": false,
                  "flipY": false,
                  "height": 45,
                  "ignoreSize": true,
                  "layoutParameter": null,
                  "opacity": 255,
                  "positionPercentX": 0.252604157,
                  "positionPercentY": -0.0238095243,
                  "positionType": 0,
                  "rotation": 0,
                  "scaleX": 1,
                  "scaleY": 1,
                  "sizePercentX": 0.5,
                  "sizePercentY": 1.07142854,
                  "sizeType": 0,
                  "tag": 58,
                  "touchAble": true,
                  "useMergedTexture": false,
                  "visible": true,
                  "width": 192,
                  "x": 97,
                  "y": -1,
                  "backGroundBox": null,
                  "backGroundBoxData": {
                    "path": "image_checkbox_lan.png",
                    "plistFile": "talkWidgetPlist.plist",
                    "resourceType": 1
                  },
                  "backGroundBoxDisabled": null,
                  "backGroundBoxDisabledData": {
                    "path": null,
                    "plistFile": null,
                    "resourceType": 0
                  },
                  "backGroundBoxSelected": null,
                  "backGroundBoxSelectedData": {
                    "path": "image_checkbox_lan.png",
                    "plistFile": "talkWidgetPlist.plist",
                    "resourceType": 1
                  },
                  "frontCross": null,
                  "frontCrossData": {
                    "path": "u_game_btn_chat_press2.png",
                    "plistFile": "talkWidgetPlist.plist",
                    "resourceType": 1
                  },
                  "frontCrossDisabled": null,
                  "frontCrossDisabledData": {
                    "path": null,
                    "plistFile": null,
                    "resourceType": 0
                  },
                  "selectedState": false
                }
              }
            ],
            "options": {
              "__type": "ImageViewSurrogate:#EditorCommon.JsonModel.Component.GUI",
              "classname": "ImageView",
              "name": "ImageTabBg",
              "ZOrder": 0,
              "actiontag": 56276018,
              "anchorPointX": 0.5,
              "anchorPointY": 0.5,
              "classType": "CocoStudio.EngineAdapterWrap.CSImageView",
              "colorB": 255,
              "colorG": 255,
              "colorR": 255,
              "customProperty": "",
              "flipX": false,
              "flipY": false,
              "height": 42,
              "ignoreSize": false,
              "layoutParameter": null,
              "opacity": 255,
              "positionPercentX": 0.00245098048,
              "positionPercentY": 0.417777777,
              "positionType": 0,
              "rotation": 0,
              "scaleX": 1,
              "scaleY": 1,
              "sizePercentX": 0.9411765,
              "sizePercentY": 0.0933333337,
              "sizeType": 0,
              "tag": 53,
              "touchAble": true,
              "useMergedTexture": false,
              "visible": true,
              "width": 384,
              "x": 1,
              "y": 188,
              "capInsetsHeight": 4,
              "capInsetsWidth": 13,
              "capInsetsX": 20,
              "capInsetsY": 20,
              "fileName": null,
              "fileNameData": {
                "path": "image_checkbox_bg.png",
                "plistFile": "talkWidgetPlist.plist",
                "resourceType": 1
              },
              "scale9Enable": true,
              "scale9Height": 42,
              "scale9Width": 384
            }
          }
        ],
        "options": {
          "__type": "ImageViewSurrogate:#EditorCommon.JsonModel.Component.GUI",
          "classname": "ImageView",
          "name": "ImageTalkBg",
          "ZOrder": 0,
          "actiontag": 35351135,
          "anchorPointX": 0.5,
          "anchorPointY": 0.5,
          "classType": "CocoStudio.EngineAdapterWrap.CSImageView",
          "colorB": 255,
          "colorG": 255,
          "colorR": 255,
          "customProperty": "",
          "flipX": false,
          "flipY": false,
          "height": 450,
          "ignoreSize": false,
          "layoutParameter": {
            "classname": null,
            "name": null,
            "align": 7,
            "gravity": 0,
            "layoutEageType": 0,
            "layoutNormalHorizontal": 0,
            "layoutNormalVertical": 0,
            "layoutParentHorizontal": 0,
            "layoutParentVertical": 0,
            "marginDown": 0,
            "marginLeft": -6,
            "marginRight": 0,
            "marginTop": 0,
            "relativeName": "ImageTalkBg",
            "relativeToName": "VisiblePanel",
            "type": 2
          },
          "opacity": 255,
          "positionPercentX": 0.174295768,
          "positionPercentY": 0.3515625,
          "positionType": 0,
          "rotation": 0,
          "scaleX": 1,
          "scaleY": 1,
          "sizePercentX": 0.35915494,
          "sizePercentY": 0.703125,
          "sizeType": 0,
          "tag": 42,
          "touchAble": false,
          "useMergedTexture": false,
          "visible": true,
          "width": 408,
          "x": 198,
          "y": 225,
          "capInsetsHeight": 2,
          "capInsetsWidth": 2,
          "capInsetsX": 35,
          "capInsetsY": 35,
          "fileName": null,
          "fileNameData": {
            "path": "u_bounced_bg1.png",
            "plistFile": "talkWidgetPlist.plist",
            "resourceType": 1
          },
          "scale9Enable": true,
          "scale9Height": 450,
          "scale9Width": 408
        }
      }
    ],
    "options": {
      "__type": "PanelSurrogate:#EditorCommon.JsonModel.Component.GUI",
      "classname": "Panel",
      "name": "VisiblePanel",
      "ZOrder": 0,
      "actiontag": -1,
      "anchorPointX": 0,
      "anchorPointY": 0,
      "classType": "CocoStudio.EngineAdapterWrap.CSPanel",
      "colorB": 255,
      "colorG": 255,
      "colorR": 255,
      "customProperty": "",
      "flipX": false,
      "flipY": false,
      "height": 640,
      "ignoreSize": false,
      "layoutParameter": null,
      "opacity": 255,
      "positionPercentX": 0,
      "positionPercentY": 0,
      "positionType": 0,
      "rotation": 0,
      "scaleX": 1,
      "scaleY": 1,
      "sizePercentX": 1,
      "sizePercentY": 1,
      "sizeType": 0,
      "tag": 3,
      "touchAble": false,
      "useMergedTexture": false,
      "visible": true,
      "width": 1136,
      "x": 0,
      "y": 0,
      "adaptScreen": false,
      "backGroundImage": null,
      "backGroundImageData": null,
      "backGroundScale9Enable": false,
      "bgColorB": 255,
      "bgColorG": 200,
      "bgColorOpacity": 0,
      "bgColorR": 150,
      "bgEndColorB": 255,
      "bgEndColorG": 200,
      "bgEndColorR": 150,
      "bgStartColorB": 255,
      "bgStartColorG": 255,
      "bgStartColorR": 255,
      "capInsetsHeight": 1,
      "capInsetsWidth": 1,
      "capInsetsX": 0,
      "capInsetsY": 0,
      "clipAble": false,
      "colorType": 1,
      "layoutType": 3,
      "vectorX": 0,
      "vectorY": -0.5
    }
  }
}